[{"name":"לחמים/צנימים","url":"https://www.shufersal.co.il/online/he/%D7%A7%D7%98%D7%92%D7%95%D7%A8%D7%99%D7%95%D7%AA/GREEN---%D7%92%D7%A8%D7%99%D7%9F/%D7%9C%D7%97%D7%9D%2C-%D7%A7%D7%A8%D7%A7%D7%A8%D7%99%D7%9D-%D7%95%D7%A4%D7%A8%D7%99%D7%9B%D7%99%D7%95%D7%AA/%D7%9C%D7%97%D7%9D%2C-%D7%A4%D7%99%D7%AA%D7%95%D7%AA-%D7%95%D7%9C%D7%97%D7%9E%D7%A0%D7%99%D7%95%D7%AA/%D7%9C%D7%97%D7%9E%D7%99%D7%9D-%D7%A6%D7%A0%D7%99%D7%9E%D7%99%D7%9D/c/F070101","products":[]},{"name":"לחמניות","url":"https://www.shufersal.co.il/online/he/%D7%A7%D7%98%D7%92%D7%95%D7%A8%D7%99%D7%95%D7%AA/GREEN---%D7%92%D7%A8%D7%99%D7%9F/%D7%9C%D7%97%D7%9D%2C-%D7%A7%D7%A8%D7%A7%D7%A8%D7%99%D7%9D-%D7%95%D7%A4%D7%A8%D7%99%D7%9B%D7%99%D7%95%D7%AA/%D7%9C%D7%97%D7%9D%2C-%D7%A4%D7%99%D7%AA%D7%95%D7%AA-%D7%95%D7%9C%D7%97%D7%9E%D7%A0%D7%99%D7%95%D7%AA/%D7%9C%D7%97%D7%9E%D7%A0%D7%99%D7%95%D7%AA/c/F070102","products":[]},{"name":"טורטיות","url":"https://www.shufersal.co.il/online/he/%D7%A7%D7%98%D7%92%D7%95%D7%A8%D7%99%D7%95%D7%AA/GREEN---%D7%92%D7%A8%D7%99%D7%9F/%D7%9C%D7%97%D7%9D%2C-%D7%A7%D7%A8%D7%A7%D7%A8%D7%99%D7%9D-%D7%95%D7%A4%D7%A8%D7%99%D7%9B%D7%99%D7%95%D7%AA/%D7%9C%D7%97%D7%9D%2C-%D7%A4%D7%99%D7%AA%D7%95%D7%AA-%D7%95%D7%9C%D7%97%D7%9E%D7%A0%D7%99%D7%95%D7%AA/%D7%98%D7%95%D7%A8%D7%98%D7%99%D7%95%D7%AA/c/F070103","products":[]},{"name":"פיתות","url":"https://www.shufersal.co.il/online/he/%D7%A7%D7%98%D7%92%D7%95%D7%A8%D7%99%D7%95%D7%AA/GREEN---%D7%92%D7%A8%D7%99%D7%9F/%D7%9C%D7%97%D7%9D%2C-%D7%A7%D7%A8%D7%A7%D7%A8%D7%99%D7%9D-%D7%95%D7%A4%D7%A8%D7%99%D7%9B%D7%99%D7%95%D7%AA/%D7%9C%D7%97%D7%9D%2C-%D7%A4%D7%99%D7%AA%D7%95%D7%AA-%D7%95%D7%9C%D7%97%D7%9E%D7%A0%D7%99%D7%95%D7%AA/%D7%A4%D7%99%D7%AA%D7%95%D7%AA/c/F070104","products":[]}]